setup.py
milight_controller/__init__.py
milight_controller/milight.py
milight_controller.egg-info/PKG-INFO
milight_controller.egg-info/SOURCES.txt
milight_controller.egg-info/dependency_links.txt
milight_controller.egg-info/top_level.txt