Metadata-Version: 1.1
Name: milight-controller
Version: 1.0.1
Summary: Controller for MiLight RGB lights
Home-page: https://github.com/jdah/milight-controller
Author: jdah
Author-email: jh@jhenriksen.net
License: MIT
Keywords: milight wifi led
Platform: UNKNOWN
Classifier: Development Status :: 5 - Production/Stable
Classifier: Intended Audience :: Developers
Classifier: License :: OSI Approved :: MIT License
Classifier: Topic :: Home Automation
Classifier: Programming Language :: Python :: 3
Classifier: Programming Language :: Python :: 3.2
Classifier: Programming Language :: Python :: 3.3
Classifier: Programming Language :: Python :: 3.4
Classifier: Programming Language :: Python :: 3.5
